{
    "/css/pages/app-email.css": "/css/pages/app-email.css?id=3b002805269759f8ac0f",
    "/css/pages/app-chat.css": "/css/pages/app-chat.css?id=d71e8a7574d980a0d8b9",
    "/css/core/menu/menu-types/vertical-overlay-menu.css": "/css/core/menu/menu-types/vertical-overlay-menu.css?id=08df8d96c952d5a47fe3",
    "/css/core/menu/menu-types/vertical-menu.css": "/css/core/menu/menu-types/vertical-menu.css?id=389e50bfa8e92abf67db",
    "/css/core/menu/menu-types/horizontal-menu.css": "/css/core/menu/menu-types/horizontal-menu.css?id=5ed6f7ac7101a0053030",
    "/css/core/colors/palette-noui.css": "/css/core/colors/palette-noui.css?id=b15b6ec8f6ce81cfbe61",
    "/css/components.css": "/css/components.css?id=87d89236c4860130cceb",
    "/css/colors.css": "/css/colors.css?id=a11e20555d0f71d00a52",
    "/css/bootstrap.css": "/css/bootstrap.css?id=81a14ba79d83fdb47fac",
    "/css/bootstrap-extended.css": "/css/bootstrap-extended.css?id=91ef1c3f19df246b5544",
    "/css/themes/semi-dark-layout.css": "/css/themes/semi-dark-layout.css?id=7b8904a19732a1791f33",
    "/css/themes/dark-layout.css": "/css/themes/dark-layout.css?id=87c2844ce6b21ba3db56",
    "/css/plugins/tour/tour.css": "/css/plugins/tour/tour.css?id=5ea39f017ecead1b6e83",
    "/css/plugins/forms/wizard.css": "/css/plugins/forms/wizard.css?id=c7cbe3ca9e14ed9dc9c0",
    "/css/plugins/forms/validation/form-validation.css": "/css/plugins/forms/validation/form-validation.css?id=3998979de58deee9cf44",
    "/css/plugins/extensions/toastr.css": "/css/plugins/extensions/toastr.css?id=5430648891c35c567511",
    "/css/plugins/extensions/swiper.css": "/css/plugins/extensions/swiper.css?id=207f333927965150c063",
    "/css/plugins/extensions/noui-slider.css": "/css/plugins/extensions/noui-slider.css?id=89e0fb6cf8d29a7d5fa6",
    "/css/plugins/extensions/ext-component-treeview.css": "/css/plugins/extensions/ext-component-treeview.css?id=051726df5e7c4693c45e",
    "/css/plugins/extensions/drag-and-drop.css": "/css/plugins/extensions/drag-and-drop.css?id=9f8a42b25f1577753770",
    "/css/plugins/extensions/context-menu.css": "/css/plugins/extensions/context-menu.css?id=b50051d33eca9d4cbb47",
    "/css/plugins/calendars/app-calendar.css": "/css/plugins/calendars/app-calendar.css?id=6e460c225517ff9d8527",
    "/css/plugins/animate/animate.css": "/css/plugins/animate/animate.css?id=e3cd3c65d397178a5573",
    "/css/pages/widgets.css": "/css/pages/widgets.css?id=58c21f1d787beda4c83e",
    "/css/pages/search.css": "/css/pages/search.css?id=001bf32b4b6643fc96ea",
    "/css/pages/page-users.css": "/css/pages/page-users.css?id=5e3553dd017eecd12f00",
    "/css/pages/page-user-profile.css": "/css/pages/page-user-profile.css?id=b6757a9a308003fb91b7",
    "/css/pages/page-knowledge-base.css": "/css/pages/page-knowledge-base.css?id=f0335ac83a5b2d6f40ee",
    "/css/pages/faq.css": "/css/pages/faq.css?id=ac0b03e3620ca3d66cfa",
    "/css/pages/dashboard-ecommerce.css": "/css/pages/dashboard-ecommerce.css?id=e3b3a9a362f8b37d82bf",
    "/css/pages/dashboard-analytics.css": "/css/pages/dashboard-analytics.css?id=abdac3e6dd78c8d7a9a4",
    "/css/pages/coming-soon.css": "/css/pages/coming-soon.css?id=b476b020824a787da776",
    "/css/pages/chart-chartist.css": "/css/pages/chart-chartist.css?id=da497d216b552d93b4a1",
    "/css/pages/authentication.css": "/css/pages/authentication.css?id=d71f4371e1df65d5acbe",
    "/css/pages/app-todo.css": "/css/pages/app-todo.css?id=e9bd9f2ea6931fd54e87",
    "/css/pages/app-kanban.css": "/css/pages/app-kanban.css?id=427a649f0f0cbbb12692",
    "/css/pages/app-invoice.css": "/css/pages/app-invoice.css?id=36b5342ba2aeeb08a3a6",
    "/css/pages/app-file-manager.css": "/css/pages/app-file-manager.css?id=9c5529533d393652dea8"
}
